{"name":"WicketKeeperTest","id":"APITests.RCBTests:WicketKeeperTest","testCaseName":"APITests.RCBTests","testSteps":[{"number":1,"description":"Read particular data: \u003cnull\u003e","duration":41,"startTime":"2023-01-20T20:33:43.210+05:30[Asia/Calcutta]","exception":{"errorType":"java.lang.NullPointerException","stackTrace":[{"declaringClass":"APISteps.RCBSteps","methodName":"readParticularData","fileName":"RCBSteps.java","lineNumber":28},{"declaringClass":"APITests.RCBTests","methodName":"WicketKeeperTest","fileName":"RCBTests.java","lineNumber":31}]},"result":"ERROR","precondition":false,"level":0},{"number":2,"description":"Team has at least one wicket keeper","duration":6,"startTime":"2023-01-20T20:33:43.271+05:30[Asia/Calcutta]","result":"SKIPPED","precondition":false,"level":0}],"userStory":{"id":"APITests.RCBTests","storyName":"RCB tests","displayName":"RCB tests","storyClassName":"APITests.RCBTests","path":"APITests","type":"story","qualifiedTag":{"name":"API tests/RCB tests","type":"story","displayName":"API tests/RCB tests"}},"featureTag":{"name":"API tests/RCB tests","type":"story","displayName":"API tests/RCB tests"},"title":"Make sure there is at least one wicket keeper in the team sheet","tags":[{"name":"API tests/RCB tests","type":"story","displayName":"API tests/RCB tests"}],"allTags":[{"name":"API tests/RCB tests","type":"story","displayName":"API tests/RCB tests"}],"startTime":"2023-01-20T20:33:42.418+05:30[Asia/Calcutta]","duration":1331,"testFailureCause":{"errorType":"java.lang.NullPointerException","stackTrace":[{"declaringClass":"APISteps.RCBSteps","methodName":"readParticularData","fileName":"RCBSteps.java","lineNumber":28},{"declaringClass":"APITests.RCBTests","methodName":"WicketKeeperTest","fileName":"RCBTests.java","lineNumber":31}]},"testFailureClassname":"java.lang.NullPointerException","testFailureSummary":"ERROR;java.lang.NullPointerException;null;RCBSteps.java","projectKey":"","annotatedResult":"ERROR","isManualTestingUpToDate":false,"manual":false,"testSource":"JUnit","order":0,"result":"ERROR"}